{"cameraMode":{"drawMode":0,"name":"Shaded","section":"Shading Mode"},"sceneLighting":true,"audioPlay":false,"sceneViewState":{"showFog":true,"showMaterialUpdate":false,"showSkybox":true,"showFlares":true,"showImageEffects":true,"showParticleSystems":true,"showVisualEffectGraphs":true,"m_FxEnabled":true},"in2DMode":false,"pivot":{"x":-226.86898803710938,"y":4.176144123077393,"z":28.972293853759767},"rotation":{"x":-0.34072303771972659,"y":-0.32181620597839358,"z":0.1253960281610489,"w":-0.874427318572998},"size":49.96712112426758,"orthographic":false}